Metadata-Version: 2.1
Name: nzl-tools
Version: 1.0.4
Summary: 工具包
Home-page: UNKNOWN
Author: nzl
Author-email: nzl0379@163.com
License: UNKNOWN
Platform: UNKNOWN
